aloe/SPE.py
aloe/__init__.py
aloe/backend.py
aloe/file_utils.py
aloe/frontend.py
aloe/model_validation.py
aloe/ASE/__init__.py
aloe/ASE/geometry.py
aloe/ASE/thermo.py
aloe/batch_opt/ANI2xt_no_rep.py
aloe/batch_opt/ANI2xt_rep.py
aloe/batch_opt/__init__.py
aloe/batch_opt/batchopt.py
aloe/embed/__init__.py
aloe/embed/embedding.py
aloe/enantiomers/__init__.py
aloe/enantiomers/enantiomer.py
aloe/isomer_generation/__init__.py
aloe/isomer_generation/isomer_engine.py
aloe/isomer_generation/tautomer.py
aloe/models/__init__.py
aloe/models/aimnet2_wb97m-d3_0.jpt
aloe/models/aimnet2_wb97m_ens_f.jpt
aloe/models/ani2xt_no_repulsion.pt
aloe/rank/__init__.py
aloe/rank/rank_utils.py
aloe/rank/ranking.py
aloe_engine-0.1.0.dist-info/licenses/LICENSE
aloe_engine-0.1.0.dist-info/METADATA
aloe_engine-0.1.0.dist-info/WHEEL
aloe_engine-0.1.0.dist-info/top_level.txt
aloe_engine-0.1.0.dist-info/RECORD
