Metadata-Version: 2.4
Name: aloe-engine
Version: 0.1.0
Summary: Asynchronous Lightweight Optimization Engine
Author-email: Ethan Tran <ethantran0815@gmail.com>, Yiwen Wang <yiwenwang9702@gmail.com>, Ron Sarma <rsarma@andrew.cmu.edu>
License: MIT License
Requires-Python: >=3.10
License-File: LICENSE
Requires-Dist: torchani
Requires-Dist: ase
Requires-Dist: tqdm
Requires-Dist: psutil
Requires-Dist: numpy>=1.26.0
Requires-Dist: pandas>=2.2.3
Requires-Dist: rdkit>=2024.3.1
Dynamic: license-file
